clldmpg/__init__.py
clldmpg/__main__.py
clldmpg/cdstar.py
clldmpg/commands/__init__.py
clldmpg/commands/dl2cdstar.py
clldmpg/static/minerva.png
clldmpg/templates/clldmpg_util.mako
clldmpg/templates/download.mako
clldmpg/templates/legal.mako
clldmpg-4.3.1.dist-info/LICENSE
clldmpg-4.3.1.dist-info/METADATA
clldmpg-4.3.1.dist-info/WHEEL
clldmpg-4.3.1.dist-info/entry_points.txt
clldmpg-4.3.1.dist-info/top_level.txt
clldmpg-4.3.1.dist-info/RECORD
